signpdf2/__init__.py
signpdf2/create_tmp_file.py
signpdf2/example.py
signpdf2/file_utilities.py
signpdf2/pdf_utilites.py
signpdf2/sign_pdf.py
signpdf2-7.0.0.dist-info/LICENSE
signpdf2-7.0.0.dist-info/METADATA
signpdf2-7.0.0.dist-info/WHEEL
signpdf2-7.0.0.dist-info/top_level.txt
signpdf2-7.0.0.dist-info/RECORD
