Metadata-Version: 2.1
Name: signpdf2
Version: 7.0.0
Summary: Sign PDFs using a signature image
Home-page: https://github.com/aseem-hegshetye/signpdf
Author: Aseem Hegshetye
Author-email: aseem.hegshetye@gmail.com
License: MIT
Classifier: License :: OSI Approved :: MIT License
Classifier: Programming Language :: Python :: 3.12
Classifier: Operating System :: OS Independent
License-File: LICENSE
Requires-Dist: pypdf
Requires-Dist: requests
Requires-Dist: urllib3
Requires-Dist: reportlab
Requires-Dist: pytz
